banks/__about__.py
banks/__init__.py
banks/cache.py
banks/config.py
banks/env.py
banks/errors.py
banks/prompt.py
banks/types.py
banks/utils.py
banks/extensions/__init__.py
banks/extensions/chat.py
banks/extensions/completion.py
banks/extensions/docs.py
banks/filters/__init__.py
banks/filters/cache_control.py
banks/filters/image.py
banks/filters/lemmatize.py
banks/filters/tool.py
banks/registries/__init__.py
banks/registries/directory.py
banks/registries/file.py
banks/registries/redis.py
banks-1.8.0.dist-info/METADATA
banks-1.8.0.dist-info/WHEEL
banks-1.8.0.dist-info/licenses/LICENSE.txt
banks-1.8.0.dist-info/RECORD
