Metadata-Version: 2.4
Name: banks
Version: 1.8.0
Summary: A prompt programming language
Project-URL: Documentation, https://github.com/unknown/banks#readme
Project-URL: Issues, https://github.com/unknown/banks/issues
Project-URL: Source, https://github.com/unknown/banks
Author-email: Massimiliano Pippi <mpippi@gmail.com>
License-Expression: MIT
License-File: LICENSE.txt
Classifier: Development Status :: 4 - Beta
Classifier: Programming Language :: Python
Classifier: Programming Language :: Python :: 3.9
Classifier: Programming Language :: Python :: 3.10
Classifier: Programming Language :: Python :: 3.11
Classifier: Programming Language :: Python :: 3.12
Classifier: Programming Language :: Python :: Implementation :: CPython
Classifier: Programming Language :: Python :: Implementation :: PyPy
Requires-Python: >=3.9
Requires-Dist: deprecated
Requires-Dist: eval-type-backport; python_version < '3.10'
Requires-Dist: griffe
Requires-Dist: jinja2
Requires-Dist: litellm
Requires-Dist: pydantic
Requires-Dist: redis
Provides-Extra: minimal
Requires-Dist: deprecated; extra == 'minimal'
Requires-Dist: eval-type-backport; (python_version < '3.10') and extra == 'minimal'
Requires-Dist: griffe; extra == 'minimal'
Requires-Dist: jinja2; extra == 'minimal'
Requires-Dist: pydantic; extra == 'minimal'
